axlnlp/__init__.py
axlnlp/logger.py
axlnlp/split_utils.py
axlnlp/utils.py
axlnlp/dataset/__init__.py
axlnlp/dataset/dataset.py
axlnlp/dataset/encoders.py
axlnlp/dataset/featureset.py
axlnlp/dataset/preprocessor.py
axlnlp/datasets/__init__.py
axlnlp/datasets/pe.py
axlnlp/evaluation/__init__.py
axlnlp/evaluation/evaluator.py
axlnlp/features/__init__.py
axlnlp/features/base.py
axlnlp/features/bow.py
axlnlp/features/document_positions.py
axlnlp/features/embeddings.py
axlnlp/models/__init__.py
axlnlp/models/base.py
axlnlp/models/bert_token_clf.py
axlnlp/models/lstm.py
axlnlp/models/lstm_cnn_crf.py
axlnlp/models/lstm_crf.py
axlnlp/training/__init__.py
axlnlp/training/custom_loggers.py
axlnlp/training/trainer.py
axlnlp/visualization/__init__.py
AxlNLP-0.0.1.dist-info/METADATA
AxlNLP-0.0.1.dist-info/WHEEL
AxlNLP-0.0.1.dist-info/top_level.txt
AxlNLP-0.0.1.dist-info/RECORD
