Metadata-Version: 2.1
Name: AxlNLP
Version: 0.0.1
Summary: my nlp tools
Home-page: https://github.com/AxlAlm/AxlNLP
Author: Axel Almquist
Author-email: axelalmquist@gmail.com
License: UNKNOWN
Platform: UNKNOWN
Classifier: Programming Language :: Python :: 3
Classifier: License :: OSI Approved :: MIT License
Classifier: Operating System :: OS Independent
Requires-Python: >=3.7
Requires-Dist: numpy (==1.18.1)
Requires-Dist: pytorch-lightning (==0.7.3)
Requires-Dist: gensim (==3.8.1)
Requires-Dist: spacy (==2.2.3)
Requires-Dist: regex (==2020.1.8)
Requires-Dist: nltk (==3.4.5)
Requires-Dist: torch (==1.4.0)
Requires-Dist: comet-ml (==3.1.4)
Requires-Dist: pytorch-crf (==0.7.2)
Requires-Dist: flair (==0.4.5)
Requires-Dist: scikit-learn (==0.22.1)
Requires-Dist: pandas (==1.0.1)
Requires-Dist: colorama (==0.4.3)
Requires-Dist: Pillow (==7.1.2)
Requires-Dist: swifter (==0.304)
Requires-Dist: transformers (==2.11.0)
